{
  "awards": [
    {
      "src": "images/awards/award1.png",
      "alt": "Outstanding Drama Series -- EMMY Awards"
    },
    {
      "src": "images/awards/award2.png",
      "alt": "Best Drama Series -- Critic's Choice Television Awards"
    },
    {
      "src": "images/awards/award3.png",
      "alt": "Best Television Series - Drama -- Golden Globe Awards"
    },
    {
      "src": "images/awards/award4.png",
      "alt": "Best Television Series - Drama -- IGN Awards"
    },
    {
      "src": "images/awards/award5.png",
      "alt": "Program of the Year -- 2016 TCA Awards"
    },
    {
      "src": "images/awards/award6.png",
      "alt": "Top 10 TV Programs -- American Film Institute Awards"
    },
    {
      "src": "images/awards/award7.png",
      "alt": "Most Pirated TV Program -- Guinness World Records"
    },
    {
      "src": "images/awards/award8.png",
      "alt": "Best Fantasy TV Series -- Dragon Awards"
    },
    {
      "src": "images/awards/award9.png",
      "alt": "Best International TV Series -- Jupiter Awards"
    },
    {
      "src": "images/awards/award10.png",
      "alt": "Best International Show -- TV Choice Awards"
    },
    {
      "src": "images/awards/award11.png",
      "alt": "Best Show -- MTV Movie and TV Awards"
    }
  ]
}
